zxc.py
zxc-0.0.1.dist-info/WHEEL
zxc-0.0.1.dist-info/METADATA
zxc-0.0.1.dist-info/RECORD
