Metadata-Version: 2.1
Name: zxc
Version: 0.0.1
Summary: 1000-7 calculyator
Author: fikko
Requires-Python: >=3.10,<4.0
Classifier: Programming Language :: Python :: 3
Classifier: Programming Language :: Python :: 3.10
